cufinder/__init__.py
cufinder/base_api_client.py
cufinder/client.py
cufinder/exceptions.py
cufinder/sdk.py
cufinder/types.py
cufinder/models/__init__.py
cufinder/models/base.py
cufinder/models/company.py
cufinder/models/person.py
cufinder/models/responses.py
cufinder/services/__init__.py
cufinder/services/base.py
cufinder/services/bcd.py
cufinder/services/car.py
cufinder/services/cbc.py
cufinder/services/ccp.py
cufinder/services/cec.py
cufinder/services/clo.py
cufinder/services/csc.py
cufinder/services/cse.py
cufinder/services/csn.py
cufinder/services/cuf.py
cufinder/services/dtc.py
cufinder/services/dte.py
cufinder/services/elf.py
cufinder/services/enc.py
cufinder/services/epp.py
cufinder/services/fcc.py
cufinder/services/fcl.py
cufinder/services/fts.py
cufinder/services/fwe.py
cufinder/services/isc.py
cufinder/services/lbs.py
cufinder/services/lcuf.py
cufinder/services/naa.py
cufinder/services/nao.py
cufinder/services/ntp.py
cufinder/services/pse.py
cufinder/services/rel.py
cufinder/services/tep.py
cufinder_py-1.1.1.dist-info/licenses/LICENSE
cufinder_py-1.1.1.dist-info/METADATA
cufinder_py-1.1.1.dist-info/WHEEL
cufinder_py-1.1.1.dist-info/top_level.txt
cufinder_py-1.1.1.dist-info/RECORD
