Metadata-Version: 2.4
Name: cufinder-py
Version: 1.1.1
Summary: Python SDK for the CUFinder API.
Home-page: https://github.com/CUFinder/cufinder-py
Author: Cufinder Team
Author-email: CUFinder Team <support@cufinder.io>
License: MIT
Project-URL: Homepage, https://github.com/CUFinder/cufinder-py
Project-URL: Documentation, https://apidoc.cufinder.io/
Project-URL: Repository, https://github.com/CUFinder/cufinder-py.git
Project-URL: Bug Reports, https://github.com/CUFinder/cufinder-py/issues
Keywords: cufinder,cufinder-sdk,python-sdk
Classifier: Development Status :: 5 - Production/Stable
Classifier: Intended Audience :: Developers
Classifier: Topic :: Software Development :: Libraries :: Python Modules
Classifier: License :: OSI Approved :: MIT License
Classifier: Programming Language :: Python :: 3
Classifier: Programming Language :: Python :: 3.8
Classifier: Programming Language :: Python :: 3.9
Classifier: Programming Language :: Python :: 3.10
Classifier: Programming Language :: Python :: 3.11
Classifier: Programming Language :: Python :: 3.12
Classifier: Operating System :: OS Independent
Requires-Python: >=3.8
License-File: LICENSE
Requires-Dist: requests>=2.28.0
Requires-Dist: pydantic>=2.0.0
Requires-Dist: typing-extensions>=4.0.0
Provides-Extra: dev
Requires-Dist: pytest>=7.0.0; extra == "dev"
Requires-Dist: pytest-asyncio>=0.21.0; extra == "dev"
Requires-Dist: pytest-cov>=4.0.0; extra == "dev"
Requires-Dist: black>=23.0.0; extra == "dev"
Requires-Dist: isort>=5.12.0; extra == "dev"
Requires-Dist: flake8>=6.0.0; extra == "dev"
Requires-Dist: mypy>=1.0.0; extra == "dev"
Requires-Dist: types-requests>=2.28.0; extra == "dev"
Dynamic: author
Dynamic: home-page
Dynamic: license-file
Dynamic: requires-python
